{
  "freeTextAnnotations": [
    {
      "id": "freeText_1771855032578",
      "text": "Core",
      "position": {
        "x": 470.4970884162518,
        "y": 188.709575216523
      },
      "fontSize": 36,
      "fontColor": "#02d437",
      "fontWeight": "normal",
      "fontStyle": "normal",
      "textDecoration": "none",
      "textAlign": "center",
      "fontFamily": "Arial",
      "width": 138,
      "height": 137
    },
    {
      "id": "freeText_1771855146787",
      "text": "North POP",
      "position": {
        "x": 459.51250047700216,
        "y": -190.2293507104255
      },
      "fontSize": 30,
      "fontColor": "#02d437",
      "fontWeight": "normal",
      "fontStyle": "normal",
      "textDecoration": "none",
      "textAlign": "center",
      "fontFamily": "Arial"
    },
    {
      "id": "freeText_1771855473362",
      "text": "East POP",
      "position": {
        "x": 949.1397322173239,
        "y": 39.34087573607586
      },
      "fontSize": 30,
      "fontColor": "#02d437",
      "fontWeight": "normal",
      "fontStyle": "normal",
      "textDecoration": "none",
      "textAlign": "center",
      "fontFamily": "Arial"
    },
    {
      "id": "freeText_1771855488004",
      "text": "West POP",
      "position": {
        "x": -9.526672106146151,
        "y": 38.566434962907465
      },
      "fontSize": 30,
      "fontColor": "#02d437",
      "fontWeight": "normal",
      "fontStyle": "normal",
      "textDecoration": "none",
      "textAlign": "center",
      "fontFamily": "Arial"
    },
    {
      "id": "freeText_1771855509437",
      "text": "South POP",
      "position": {
        "x": 461.9741990461931,
        "y": 836.6319490672764
      },
      "fontSize": 30,
      "fontColor": "#02d437",
      "fontWeight": "normal",
      "fontStyle": "normal",
      "textDecoration": "none",
      "textAlign": "center",
      "fontFamily": "Arial"
    },
    {
      "id": "freeText_1772043594855",
      "text": "IP: **10.20.20.102/24**",
      "position": {
        "x": 1498.2375058398081,
        "y": 595.4911645163423
      },
      "fontSize": 14,
      "fontColor": "#000000",
      "backgroundColor": "#f5f5f5",
      "fontWeight": "normal",
      "fontStyle": "normal",
      "textDecoration": "none",
      "textAlign": "left",
      "fontFamily": "Arial"
    },
    {
      "id": "freeText_1772044216677",
      "text": "- Service: **L3VPN (IPVPN)**\n- Service: **MVPN  (Profile 12)**\n- VRF: **RED**\n- RT: **1:1**",
      "position": {
        "x": -1135.3374909819622,
        "y": -176.32537319213066
      },
      "fontSize": 14,
      "fontColor": "#000000",
      "backgroundColor": "#f5f5f5",
      "fontWeight": "normal",
      "fontStyle": "normal",
      "textDecoration": "none",
      "textAlign": "left",
      "fontFamily": "Arial"
    },
    {
      "id": "freeText_1772044272364",
      "text": "- Service: **E-LAN (EVPN)**\n- EVI: **VLAN 10**\n- RT: **10010:10010**",
      "position": {
        "x": -1129.1038600243403,
        "y": -648.0079130219682
      },
      "fontSize": 14,
      "fontColor": "#000000",
      "backgroundColor": "#f5f5f5",
      "fontWeight": "normal",
      "fontStyle": "normal",
      "textDecoration": "none",
      "textAlign": "left",
      "fontFamily": "Arial"
    },
    {
      "id": "freeText_1772044515114",
      "text": "- Service: **L3VPN (EVPN)**\n- VRF: **BLUE**\n- IPVRF **RT: 2:2**",
      "position": {
        "x": -1124.5866893280456,
        "y": 73.88481554485313
      },
      "fontSize": 14,
      "fontColor": "#000000",
      "backgroundColor": "#f5f5f5",
      "fontWeight": "normal",
      "fontStyle": "normal",
      "textDecoration": "none",
      "textAlign": "left",
      "fontFamily": "Arial"
    },
    {
      "id": "freeText_1772047166126",
      "text": "- Service: **E-LINE (VPWS)**\n- EVI: **ORANGE**\n- IPVRF RT: **8001:8001**",
      "position": {
        "x": -1134.761969333374,
        "y": -406.06743962787357
      },
      "fontSize": 14,
      "fontColor": "#000000",
      "backgroundColor": "#f5f5f5",
      "fontWeight": "normal",
      "fontStyle": "normal",
      "textDecoration": "none",
      "textAlign": "left",
      "fontFamily": "Arial"
    },
    {
      "id": "freeText_1772047341537",
      "text": "## Overview\n- Transport: ISIS-SR\n  - SRGB: 900000 - 965535\n  - Node SID: 900000 + NodeID\n- BGP ASN: 100\n- Loopback0: 100.0.0.X\n- Point-to-Point: 20.X.Y.Z/24\n  - X: Low Node ID\n  - Y: High Node ID\n  - Z: Node ID\n",
      "position": {
        "x": -795.6270072695233,
        "y": -678.5641829564833
      },
      "fontSize": 14,
      "fontColor": "#000000",
      "backgroundColor": "#f5f5f5",
      "fontWeight": "normal",
      "fontStyle": "normal",
      "textDecoration": "none",
      "textAlign": "left",
      "fontFamily": "Arial"
    },
    {
      "id": "freeText_1772050363923",
      "text": "- Multihoming: **All-Active**\n- EVI: **ORANGE (VPWS)**\n- ESI: **0000:0010:0011:0500:0000**\n- RT: **00:00:10:00:11:05**",
      "position": {
        "x": 438.3745291404514,
        "y": -467.28048513691317
      },
      "fontSize": 10,
      "fontColor": "#3b3b3b",
      "backgroundColor": "#f5f5f5",
      "fontWeight": "normal",
      "fontStyle": "normal",
      "textDecoration": "none",
      "textAlign": "left",
      "fontFamily": "Arial",
      "rotation": 0
    },
    {
      "id": "freeText_1772050945209",
      "text": "- Multihoming: **All-Active**\n- EVI: **VLAN 20**\n- MAC-VRF RT: **10020:10020**\n- ESI: **0000:0012:0013:0500:0000**\n- ES RT: **00:00:12:00:13:05**\n- IRB: **Yes**",
      "position": {
        "x": 1182.2709399653145,
        "y": 320.45016471156333
      },
      "fontSize": 10,
      "fontColor": "#3b3b3b",
      "backgroundColor": "#f5f5f5",
      "fontWeight": "normal",
      "fontStyle": "normal",
      "textDecoration": "none",
      "textAlign": "left",
      "fontFamily": "Arial"
    },
    {
      "id": "freeText_1772051028886",
      "text": "- Multihoming: **All-Active**\n- EVI: **VLAN 10**\n- MAC-VRF RT: **10010:10010**\n- ESI: **0000:0016:0017:0500:0000**\n- ES RT: **00:00:16:00:17:05**\n- IRB: **No**",
      "position": {
        "x": -306.76533802818903,
        "y": 320.7143087980439
      },
      "fontSize": 10,
      "fontColor": "#3b3b3b",
      "backgroundColor": "#f5f5f5",
      "fontWeight": "normal",
      "fontStyle": "normal",
      "textDecoration": "none",
      "textAlign": "left",
      "fontFamily": "Arial"
    },
    {
      "id": "freeText_1772051622115",
      "text": "- Multihoming: **All-Active**\n- EVI: **ORANGE (VPWS)**\n- ESI: **0000:0014:0015:0500:0000**\n- RT: **00:00:14:00:15:05**",
      "position": {
        "x": 438.40495096868665,
        "y": 1135.7758668954734
      },
      "fontSize": 10,
      "fontColor": "#3b3b3b",
      "backgroundColor": "#f5f5f5",
      "fontWeight": "normal",
      "fontStyle": "normal",
      "textDecoration": "none",
      "textAlign": "left",
      "fontFamily": "Arial"
    }
  ],
  "freeShapeAnnotations": [
    {
      "id": "freeShape_1771854712687",
      "shapeType": "rectangle",
      "position": {
        "x": 239.18275716241794,
        "y": 75.39249837391279
      },
      "width": 599,
      "height": 607,
      "fillColor": "#ababab",
      "fillOpacity": 0.2,
      "borderColor": "#b3b3b3",
      "borderWidth": 0,
      "borderStyle": "solid",
      "rotation": 0,
      "zIndex": -1
    },
    {
      "id": "freeShape_1771854883444",
      "shapeType": "rectangle",
      "position": {
        "x": 941.3929884237441,
        "y": 74.13296659925936
      },
      "width": 150,
      "height": 605,
      "fillColor": "#ababab",
      "fillOpacity": 0.2,
      "borderColor": "#d4d4d4",
      "borderWidth": 1,
      "borderStyle": "solid",
      "rotation": 0,
      "zIndex": -1
    },
    {
      "id": "freeShape_1771854955406",
      "shapeType": "rectangle",
      "position": {
        "x": 238.65080411030695,
        "y": -161.39565567831534
      },
      "width": 599,
      "height": 121,
      "fillColor": "#ababab",
      "fillOpacity": 0.2,
      "borderColor": "#d4d4d4",
      "borderWidth": 1,
      "borderStyle": "solid",
      "rotation": 0,
      "zIndex": -1
    },
    {
      "id": "freeShape_1771854990011",
      "shapeType": "rectangle",
      "position": {
        "x": -15.48816419839352,
        "y": 74.81453185083802
      },
      "width": 150,
      "height": 606,
      "fillColor": "#ababab",
      "fillOpacity": 0.2,
      "borderColor": "#d4d4d4",
      "borderWidth": 1,
      "borderStyle": "solid",
      "rotation": 0,
      "zIndex": -1
    },
    {
      "id": "freeShape_1771855013839",
      "shapeType": "rectangle",
      "position": {
        "x": 198.9633168486634,
        "y": 800.0316465340774
      },
      "width": 679,
      "height": 116,
      "fillColor": "#ababab",
      "fillOpacity": 0.2,
      "borderColor": "#d4d4d4",
      "borderWidth": 1,
      "borderStyle": "solid",
      "rotation": 0,
      "zIndex": -1
    },
    {
      "id": "freeShape_1772043036512",
      "shapeType": "rectangle",
      "position": {
        "x": 198.0997270846819,
        "y": -439.70933463535556
      },
      "width": 200,
      "height": 200,
      "fillColor": "#fe7070",
      "fillOpacity": 0.75,
      "borderColor": "#3b3b3b",
      "borderWidth": 0,
      "borderStyle": "solid",
      "rotation": 0,
      "cornerRadius": 25,
      "zIndex": -1
    },
    {
      "id": "freeShape_1772043638180",
      "shapeType": "rectangle",
      "position": {
        "x": 1158.7053291768937,
        "y": 518.2287335468033
      },
      "width": 200,
      "height": 200,
      "fillColor": "#fe7070",
      "fillOpacity": 0.75,
      "borderColor": "#3b3b3b",
      "borderWidth": 0,
      "borderStyle": "solid",
      "rotation": 90,
      "cornerRadius": 25,
      "zIndex": -1
    },
    {
      "id": "freeShape_1772043864497",
      "shapeType": "rectangle",
      "position": {
        "x": 681.2345639954103,
        "y": -440.97659529667516
      },
      "width": 200,
      "height": 200,
      "fillColor": "#AEAEC0",
      "fillOpacity": 0.75,
      "borderColor": "#3b3b3b",
      "borderWidth": 0,
      "borderStyle": "solid",
      "rotation": 0,
      "cornerRadius": 25,
      "zIndex": -1
    },
    {
      "id": "freeShape_1772044153073",
      "shapeType": "rectangle",
      "position": {
        "x": -1161.777802823754,
        "y": -680.6581473137162
      },
      "width": 280,
      "height": 160,
      "fillColor": "#ffd166",
      "fillOpacity": 0.75,
      "borderColor": "#3b3b3b",
      "borderWidth": 0,
      "borderStyle": "solid",
      "rotation": 0,
      "cornerRadius": 25,
      "zIndex": -1
    },
    {
      "id": "freeShape_1772044160876",
      "shapeType": "rectangle",
      "position": {
        "x": -1162.3962536591375,
        "y": -199.84189829887765
      },
      "width": 280,
      "height": 160,
      "fillColor": "#fe7070",
      "fillOpacity": 0.75,
      "borderColor": "#3b3b3b",
      "borderWidth": 0,
      "borderStyle": "solid",
      "rotation": 0,
      "cornerRadius": 25,
      "zIndex": -1
    },
    {
      "id": "freeShape_1772044184309",
      "shapeType": "rectangle",
      "position": {
        "x": -1161.7736099566748,
        "y": 38.65080560824765
      },
      "width": 280,
      "height": 160,
      "fillColor": "#635dff",
      "fillOpacity": 0.75,
      "borderColor": "#3b3b3b",
      "borderWidth": 0,
      "borderStyle": "solid",
      "rotation": 0,
      "cornerRadius": 25,
      "zIndex": -1
    },
    {
      "id": "freeShape_1772045199963",
      "shapeType": "rectangle",
      "position": {
        "x": 1359.2448581496321,
        "y": 278.3881560368921
      },
      "width": 200,
      "height": 200,
      "fillColor": "#635dff",
      "fillOpacity": 0.75,
      "borderColor": "#3b3b3b",
      "borderWidth": 0,
      "borderStyle": "solid",
      "rotation": 0,
      "cornerRadius": 25,
      "zIndex": -1
    },
    {
      "id": "freeShape_1772045444795",
      "shapeType": "rectangle",
      "position": {
        "x": -280.72110289910614,
        "y": 38.82266203037756
      },
      "width": 200,
      "height": 200,
      "fillColor": "#635dff",
      "fillOpacity": 0.75,
      "borderColor": "#3b3b3b",
      "borderWidth": 0,
      "borderStyle": "solid",
      "rotation": 0,
      "cornerRadius": 25,
      "zIndex": -1
    },
    {
      "id": "freeShape_1772045486871",
      "shapeType": "rectangle",
      "position": {
        "x": 1157.975104857378,
        "y": 39.292951880688975
      },
      "width": 200,
      "height": 200,
      "fillColor": "#ffd166",
      "fillOpacity": 0.75,
      "borderColor": "#3b3b3b",
      "borderWidth": 0,
      "borderStyle": "solid",
      "rotation": 0,
      "cornerRadius": 25,
      "zIndex": -1
    },
    {
      "id": "freeShape_1772045502084",
      "shapeType": "rectangle",
      "position": {
        "x": -479.8075792826584,
        "y": 279.7448597461035
      },
      "width": 200,
      "height": 200,
      "fillColor": "#ffd166",
      "fillOpacity": 0.75,
      "borderColor": "#3b3b3b",
      "borderWidth": 0,
      "borderStyle": "solid",
      "rotation": 0,
      "cornerRadius": 25,
      "zIndex": -1
    },
    {
      "id": "freeShape_1772045553707",
      "shapeType": "rectangle",
      "position": {
        "x": -1164.7362902362,
        "y": -439.0805786301615
      },
      "width": 280,
      "height": 160,
      "fillColor": "#F4A261",
      "fillOpacity": 0.75,
      "borderColor": "#3b3b3b",
      "borderWidth": 0,
      "borderStyle": "solid",
      "rotation": 0,
      "cornerRadius": 25,
      "zIndex": -1
    },
    {
      "id": "freeShape_1772045620904",
      "shapeType": "rectangle",
      "position": {
        "x": 439.786940217885,
        "y": -639.0971057543493
      },
      "width": 200,
      "height": 200,
      "fillColor": "#F4A261",
      "fillOpacity": 0.75,
      "borderColor": "#3b3b3b",
      "borderWidth": 0,
      "borderStyle": "solid",
      "rotation": 0,
      "cornerRadius": 25,
      "zIndex": -1
    },
    {
      "id": "freeShape_1772045643066",
      "shapeType": "rectangle",
      "position": {
        "x": 439.67908288364447,
        "y": 1199.644217510482
      },
      "width": 200,
      "height": 200,
      "fillColor": "#F4A261",
      "fillOpacity": 0.75,
      "borderColor": "#3b3b3b",
      "borderWidth": 0,
      "borderStyle": "solid",
      "rotation": 0,
      "cornerRadius": 25,
      "zIndex": -1
    },
    {
      "id": "freeShape_1772046760757",
      "shapeType": "rectangle",
      "position": {
        "x": -280.33284138590693,
        "y": 519.2799210977037
      },
      "width": 200,
      "height": 200,
      "fillColor": "#fe7070",
      "fillOpacity": 0.75,
      "borderColor": "#3b3b3b",
      "borderWidth": 0,
      "borderStyle": "solid",
      "rotation": 0,
      "cornerRadius": 25,
      "zIndex": -1
    },
    {
      "id": "freeShape_1772046804274",
      "shapeType": "rectangle",
      "position": {
        "x": 199.8116466637311,
        "y": 999.8646007867533
      },
      "width": 200,
      "height": 200,
      "fillColor": "#635dff",
      "fillOpacity": 0.75,
      "borderColor": "#3b3b3b",
      "borderWidth": 0,
      "borderStyle": "solid",
      "rotation": 0,
      "cornerRadius": 25,
      "zIndex": -1
    },
    {
      "id": "freeShape_1772047462845",
      "shapeType": "rectangle",
      "position": {
        "x": 679.6634683895302,
        "y": 999.5156874612139
      },
      "width": 200,
      "height": 200,
      "fillColor": "#ffd166",
      "fillOpacity": 0.75,
      "borderColor": "#3b3b3b",
      "borderWidth": 0,
      "borderStyle": "solid",
      "rotation": 0,
      "cornerRadius": 25,
      "zIndex": -1
    }
  ],
  "groupStyleAnnotations": [],
  "networkNodeAnnotations": [],
  "nodeAnnotations": [
    {
      "id": "PE-7",
      "position": {
        "x": 280,
        "y": 600
      },
      "geoCoordinates": {
        "lat": 48.775846,
        "lng": 9.182932
      },
      "icon": "pe",
      "iconColor": "#16325b",
      "iconCornerRadius": 40
    },
    {
      "id": "PE-1",
      "position": {
        "x": 280,
        "y": 120
      },
      "geoCoordinates": {
        "lat": 50.110924,
        "lng": 8.682127
      },
      "icon": "pe",
      "iconColor": "#16325b",
      "iconCornerRadius": 40
    },
    {
      "id": "PE-6",
      "position": {
        "x": 520,
        "y": 600
      },
      "geoCoordinates": {
        "lat": 48.856613,
        "lng": 2.352222
      },
      "icon": "pe",
      "iconColor": "#16325b",
      "iconCornerRadius": 40
    },
    {
      "id": "PE-2",
      "position": {
        "x": 520,
        "y": 120
      },
      "geoCoordinates": {
        "lat": 51.507351,
        "lng": -0.127758
      },
      "icon": "pe",
      "iconColor": "#16325b",
      "iconCornerRadius": 40
    },
    {
      "id": "PE-5",
      "position": {
        "x": 760,
        "y": 600
      },
      "geoCoordinates": {
        "lat": 48.775846,
        "lng": 11.982932
      },
      "icon": "pe",
      "iconColor": "#16325b",
      "iconCornerRadius": 40
    },
    {
      "id": "PE-3",
      "position": {
        "x": 760,
        "y": 120
      },
      "geoCoordinates": {
        "lat": 50.110924,
        "lng": 11.482127
      },
      "icon": "pe",
      "iconColor": "#16325b",
      "iconCornerRadius": 40
    },
    {
      "id": "PE-17",
      "position": {
        "x": 40,
        "y": 120
      },
      "geoCoordinates": {
        "lat": 48.856613,
        "lng": 5.152222
      },
      "icon": "pe",
      "iconColor": "#16325b",
      "iconCornerRadius": 40
    },
    {
      "id": "CE-8",
      "position": {
        "x": 1440,
        "y": 360
      },
      "geoCoordinates": {
        "lat": 52.090823,
        "lng": 10.662026
      },
      "icon": "pe",
      "iconColor": "#16325b",
      "iconCornerRadius": 0
    },
    {
      "id": "PE-10",
      "position": {
        "x": 280,
        "y": -120
      },
      "icon": "pe",
      "iconColor": "#16325b",
      "interfacePattern": "et{n}",
      "iconCornerRadius": 40
    },
    {
      "id": "PE-15",
      "position": {
        "x": 280,
        "y": 840
      },
      "icon": "pe",
      "iconColor": "#16325b",
      "interfacePattern": "et{n}",
      "iconCornerRadius": 40
    },
    {
      "id": "PE-11",
      "position": {
        "x": 760,
        "y": -120
      },
      "icon": "pe",
      "iconColor": "#16325b",
      "interfacePattern": "et{n}",
      "iconCornerRadius": 40
    },
    {
      "id": "PE-14",
      "position": {
        "x": 760,
        "y": 840
      },
      "icon": "pe",
      "iconColor": "#16325b",
      "interfacePattern": "et{n}",
      "iconCornerRadius": 40
    },
    {
      "id": "PE-16",
      "position": {
        "x": 40,
        "y": 600
      },
      "icon": "pe",
      "iconColor": "#16325b",
      "interfacePattern": "et{n}",
      "iconCornerRadius": 40
    },
    {
      "id": "PE-13",
      "position": {
        "x": 1000,
        "y": 600
      },
      "icon": "pe",
      "iconColor": "#16325b",
      "interfacePattern": "et{n}",
      "iconCornerRadius": 40
    },
    {
      "id": "PE-12",
      "position": {
        "x": 1000,
        "y": 120
      },
      "icon": "pe",
      "iconColor": "#16325b",
      "interfacePattern": "et{n}",
      "iconCornerRadius": 40
    },
    {
      "id": "CE-5",
      "position": {
        "x": 520,
        "y": -560
      },
      "icon": "pe",
      "iconColor": "#16325b",
      "interfacePattern": "et{n}"
    },
    {
      "id": "CE-11",
      "position": {
        "x": 520,
        "y": 1280
      },
      "icon": "pe",
      "iconColor": "#16325b",
      "interfacePattern": "et{n}"
    },
    {
      "id": "CE-4",
      "position": {
        "x": 280,
        "y": -360
      },
      "icon": "pe",
      "iconColor": "#16325b",
      "interfacePattern": "et{n}"
    },
    {
      "id": "CE-6",
      "position": {
        "x": 760,
        "y": -360
      },
      "icon": "pe",
      "iconColor": "#16325b",
      "interfacePattern": "et{n}"
    },
    {
      "id": "CE-2",
      "position": {
        "x": -400,
        "y": 360
      },
      "icon": "pe",
      "iconColor": "#16325b",
      "interfacePattern": "et{n}"
    },
    {
      "id": "CE-1",
      "position": {
        "x": -200,
        "y": 600
      },
      "icon": "pe",
      "iconColor": "#16325b",
      "interfacePattern": "et{n}"
    },
    {
      "id": "CE-7",
      "position": {
        "x": 1240,
        "y": 120
      },
      "icon": "pe",
      "iconColor": "#16325b",
      "interfacePattern": "et{n}"
    },
    {
      "id": "CE-9",
      "position": {
        "x": 1240,
        "y": 600
      },
      "icon": "pe",
      "iconColor": "#16325b",
      "interfacePattern": "et{n}"
    },
    {
      "id": "CE-12",
      "position": {
        "x": 280,
        "y": 1080
      },
      "icon": "pe",
      "iconColor": "#16325b",
      "interfacePattern": "et{n}"
    },
    {
      "id": "CE-10",
      "position": {
        "x": 760,
        "y": 1080
      },
      "icon": "pe",
      "iconColor": "#16325b",
      "interfacePattern": "et{n}"
    },
    {
      "id": "CE-3",
      "position": {
        "x": -200,
        "y": 120
      },
      "icon": "pe",
      "iconColor": "#16325b",
      "interfacePattern": "et{n}"
    },
    {
      "id": "PE-8",
      "position": {
        "x": 280,
        "y": 360
      },
      "icon": "pe",
      "interfacePattern": "et{n}",
      "iconCornerRadius": 40,
      "iconColor": "#16325b"
    },
    {
      "id": "PE-4",
      "position": {
        "x": 760,
        "y": 360
      },
      "icon": "pe",
      "interfacePattern": "et{n}",
      "iconCornerRadius": 40,
      "iconColor": "#16325b"
    },
    {
      "id": "PE-9",
      "position": {
        "x": 520,
        "y": 360
      },
      "icon": "pe",
      "interfacePattern": "et{n}",
      "iconCornerRadius": 40,
      "iconColor": "#16325b"
    },
    {
      "id": "Host4",
      "position": {
        "x": 280,
        "y": -520
      },
      "icon": "client",
      "iconColor": "#16325b",
      "interfacePattern": "eth{n}",
      "iconCornerRadius": 0
    },
    {
      "id": "Host1",
      "position": {
        "x": -400,
        "y": 600
      },
      "icon": "client",
      "iconColor": "#16325b",
      "interfacePattern": "eth{n}"
    },
    {
      "id": "Host5",
      "position": {
        "x": 520,
        "y": -720
      },
      "icon": "client",
      "iconColor": "#16325b",
      "interfacePattern": "eth{n}"
    },
    {
      "id": "Host6",
      "position": {
        "x": 760,
        "y": -520
      },
      "icon": "client",
      "iconColor": "#16325b",
      "interfacePattern": "eth{n}"
    },
    {
      "id": "host7",
      "position": {
        "x": 1400,
        "y": 120
      },
      "icon": "client",
      "iconColor": "#16325b",
      "interfacePattern": "eth{n}"
    },
    {
      "id": "host8",
      "position": {
        "x": 1400,
        "y": 360
      },
      "icon": "client",
      "iconColor": "#16325b",
      "interfacePattern": "eth{n}"
    },
    {
      "id": "host10",
      "position": {
        "x": 760,
        "y": 1240
      },
      "icon": "client",
      "iconColor": "#16325b",
      "interfacePattern": "eth{n}"
    },
    {
      "id": "host11",
      "position": {
        "x": 520,
        "y": 1240
      },
      "icon": "client",
      "iconColor": "#16325b",
      "interfacePattern": "eth{n}"
    },
    {
      "id": "host12",
      "position": {
        "x": 280,
        "y": 1240
      },
      "icon": "client",
      "iconColor": "#16325b",
      "interfacePattern": "eth{n}"
    },
    {
      "id": "host1",
      "position": {
        "x": -360,
        "y": 600
      },
      "icon": "client",
      "iconColor": "#16325b",
      "interfacePattern": "eth{n}"
    },
    {
      "id": "host2",
      "position": {
        "x": -360,
        "y": 360
      },
      "icon": "client",
      "iconColor": "#16325b",
      "interfacePattern": "eth{n}"
    },
    {
      "id": "host3",
      "position": {
        "x": -360,
        "y": 120
      },
      "icon": "client",
      "iconColor": "#16325b",
      "interfacePattern": "eth{n}"
    },
    {
      "id": "Host12",
      "position": {
        "x": 280,
        "y": 1280
      },
      "icon": "client",
      "iconColor": "#16325b",
      "iconCornerRadius": 0
    },
    {
      "id": "Host11",
      "position": {
        "x": 520,
        "y": 1440
      },
      "icon": "client",
      "iconColor": "#16325b",
      "iconCornerRadius": 0
    },
    {
      "id": "Host10",
      "position": {
        "x": 760,
        "y": 1280
      },
      "icon": "client",
      "iconColor": "#16325b",
      "iconCornerRadius": 0
    },
    {
      "id": "Host9",
      "position": {
        "x": 1440,
        "y": 600
      },
      "icon": "client",
      "iconColor": "#16325b",
      "iconCornerRadius": 0
    },
    {
      "id": "Host8",
      "position": {
        "x": 1600,
        "y": 360
      },
      "icon": "client",
      "iconColor": "#16325b",
      "iconCornerRadius": 0
    },
    {
      "id": "Host7",
      "position": {
        "x": 1440,
        "y": 120
      },
      "icon": "client",
      "iconColor": "#16325b",
      "iconCornerRadius": 0
    },
    {
      "id": "Host3",
      "position": {
        "x": -400,
        "y": 120
      },
      "icon": "client",
      "iconColor": "#16325b",
      "iconCornerRadius": 0
    },
    {
      "id": "Host2",
      "position": {
        "x": -560,
        "y": 360
      },
      "icon": "client",
      "iconColor": "#16325b",
      "iconCornerRadius": 0
    }
  ],
  "edgeAnnotations": [
    {
      "id": "Clab-Link40",
      "source": "PE-10",
      "target": "CE-4",
      "sourceEndpoint": "et4",
      "targetEndpoint": "et1",
      "endpointLabelOffsetEnabled": true,
      "endpointLabelOffset": 40
    },
    {
      "id": "Clab-Link29",
      "source": "PE-13",
      "target": "CE-9",
      "sourceEndpoint": "et4",
      "targetEndpoint": "et1",
      "endpointLabelOffsetEnabled": true,
      "endpointLabelOffset": 40
    },
    {
      "id": "Clab-Link41",
      "source": "PE-11",
      "target": "CE-6",
      "sourceEndpoint": "et4",
      "targetEndpoint": "et1",
      "endpointLabelOffsetEnabled": true,
      "endpointLabelOffset": 40
    },
    {
      "id": "Clab-Link48",
      "source": "CE-4",
      "target": "Host4",
      "sourceEndpoint": "et2",
      "targetEndpoint": "eth1",
      "endpointLabelOffsetEnabled": true,
      "endpointLabelOffset": 40
    },
    {
      "id": "Clab-Link51",
      "source": "Host6",
      "target": "CE-6",
      "sourceEndpoint": "eth1",
      "targetEndpoint": "et2",
      "endpointLabelOffsetEnabled": true,
      "endpointLabelOffset": 40
    },
    {
      "id": "Clab-Link49",
      "source": "host9",
      "target": "CE-9",
      "sourceEndpoint": "eth1",
      "targetEndpoint": "et2",
      "endpointLabelOffsetEnabled": true,
      "endpointLabelOffset": 40
    },
    {
      "id": "Clab-Link53",
      "source": "host8",
      "target": "CE-8",
      "sourceEndpoint": "eth1",
      "targetEndpoint": "eth1",
      "endpointLabelOffsetEnabled": true,
      "endpointLabelOffset": 40
    },
    {
      "id": "Clab-Link52",
      "source": "host7",
      "target": "CE-7",
      "sourceEndpoint": "eth1",
      "targetEndpoint": "et2",
      "endpointLabelOffsetEnabled": true,
      "endpointLabelOffset": 40
    },
    {
      "id": "Clab-Link50",
      "source": "Host5",
      "target": "CE-5",
      "sourceEndpoint": "eth1",
      "targetEndpoint": "et3",
      "endpointLabelOffsetEnabled": true,
      "endpointLabelOffset": 40
    },
    {
      "id": "Clab-Link54",
      "source": "host10",
      "target": "CE-10",
      "sourceEndpoint": "eth1",
      "targetEndpoint": "et2",
      "endpointLabelOffsetEnabled": true,
      "endpointLabelOffset": 40
    },
    {
      "id": "Clab-Link55",
      "source": "host11",
      "target": "CE-11",
      "sourceEndpoint": "eth1",
      "targetEndpoint": "et3",
      "endpointLabelOffsetEnabled": true,
      "endpointLabelOffset": 40
    },
    {
      "id": "Clab-Link56",
      "source": "host12",
      "target": "CE-12",
      "sourceEndpoint": "eth1",
      "targetEndpoint": "et2",
      "endpointLabelOffsetEnabled": true,
      "endpointLabelOffset": 40
    },
    {
      "id": "Clab-Link44",
      "source": "PE-15",
      "target": "CE-12",
      "sourceEndpoint": "et4",
      "targetEndpoint": "et1",
      "endpointLabelOffsetEnabled": true,
      "endpointLabelOffset": 40
    },
    {
      "id": "Clab-Link45",
      "source": "PE-14",
      "target": "CE-10",
      "sourceEndpoint": "et4",
      "targetEndpoint": "et1",
      "endpointLabelOffsetEnabled": true,
      "endpointLabelOffset": 40
    },
    {
      "id": "Clab-Link46",
      "source": "PE-15",
      "target": "CE-11",
      "sourceEndpoint": "et5",
      "targetEndpoint": "et1",
      "endpointLabelOffsetEnabled": true,
      "endpointLabelOffset": 40
    },
    {
      "id": "Clab-Link47",
      "source": "PE-14",
      "target": "CE-11",
      "sourceEndpoint": "et5",
      "targetEndpoint": "et2",
      "endpointLabelOffsetEnabled": true,
      "endpointLabelOffset": 40
    }
  ],
  "aliasEndpointAnnotations": [],
  "viewerSettings": {}
}
